bdpan/__init__.py
bdpan/__main__.py
bdpan/client.py
bdpan/cookies.py
bdpan/exceptions.py
bdpan/progress.py
bdpan/utils.py
bdpan-1.5.0.dist-info/METADATA
bdpan-1.5.0.dist-info/WHEEL
bdpan-1.5.0.dist-info/entry_points.txt
bdpan-1.5.0.dist-info/top_level.txt
bdpan-1.5.0.dist-info/RECORD
