Metadata-Version: 2.4
Name: bdpan
Version: 1.5.0
Summary: A small Baidu Netdisk tool.
Requires-Python: >=3.9
Requires-Dist: requests>=2.28
